mongotoy/__init__.py
mongotoy/cache.py
mongotoy/db.py
mongotoy/documents.py
mongotoy/errors.py
mongotoy/expressions.py
mongotoy/fields.py
mongotoy/geodata.py
mongotoy/mappers.py
mongotoy/references.py
mongotoy/sync.py
mongotoy/types.py
mongotoy-0.1.7.dist-info/LICENSE
mongotoy-0.1.7.dist-info/METADATA
mongotoy-0.1.7.dist-info/WHEEL
mongotoy-0.1.7.dist-info/RECORD
