Metadata-Version: 2.1
Name: mongotoy
Version: 0.1.7
Summary: Comprehensive ODM for MongoDB
Home-page: https://gurcuff91.github.io/mongotoy
License: Apache-2.0
Keywords: mapping,asyncio,odm,mongodb
Author: gurcuff91
Author-email: gf.meneses91@gmail.com
Requires-Python: >=3.12,<4.0
Classifier: Framework :: AsyncIO
Classifier: Intended Audience :: Developers
Classifier: License :: OSI Approved :: Apache Software License
Classifier: Programming Language :: Python :: 3
Classifier: Programming Language :: Python :: 3.12
Classifier: Topic :: Database
Classifier: Topic :: Software Development :: Libraries :: Python Modules
Requires-Dist: motor (>=3.4.0,<4.0.0)
Requires-Dist: pymongo (>=4.6.3,<5.0.0)
Project-URL: Repository, https://github.com/gurcuff91/mongotoy
